admin/__init__.py
admin/config/config.yml
hsds/__init__.py
hsds/app.py
hsds/async_lib.py
hsds/attr_dn.py
hsds/attr_sn.py
hsds/basenode.py
hsds/chunk_crawl.py
hsds/chunk_dn.py
hsds/chunk_sn.py
hsds/chunklocator.py
hsds/config.py
hsds/ctype_dn.py
hsds/ctype_sn.py
hsds/datanode.py
hsds/datanode_lib.py
hsds/domain_crawl.py
hsds/domain_dn.py
hsds/domain_sn.py
hsds/dset_dn.py
hsds/dset_lib.py
hsds/dset_sn.py
hsds/folder_crawl.py
hsds/group_dn.py
hsds/group_sn.py
hsds/headnode.py
hsds/hsds_app.py
hsds/hsds_logger.py
hsds/link_dn.py
hsds/link_sn.py
hsds/node_runner.py
hsds/servicenode.py
hsds/servicenode_lib.py
hsds/util/__init__.py
hsds/util/arrayUtil.py
hsds/util/attrUtil.py
hsds/util/authUtil.py
hsds/util/awsLambdaClient.py
hsds/util/azureBlobClient.py
hsds/util/boolparser.py
hsds/util/chunkUtil.py
hsds/util/domainUtil.py
hsds/util/dsetUtil.py
hsds/util/fileClient.py
hsds/util/globparser.py
hsds/util/hdf5dtype.py
hsds/util/httpUtil.py
hsds/util/idUtil.py
hsds/util/jwtUtil.py
hsds/util/k8sClient.py
hsds/util/linkUtil.py
hsds/util/lruCache.py
hsds/util/query_marathon.py
hsds/util/rangegetUtil.py
hsds/util/s3Client.py
hsds/util/storUtil.py
hsds/util/timeUtil.py
hsds-0.9.4.dist-info/licenses/LICENSE
hsds-0.9.4.dist-info/METADATA
hsds-0.9.4.dist-info/WHEEL
hsds-0.9.4.dist-info/entry_points.txt
hsds-0.9.4.dist-info/top_level.txt
hsds-0.9.4.dist-info/RECORD
